<?xml version="1.0" encoding="ISO-8859-1" standalone="no"?>
<enseignements>
<nom>ANGLAIS</nom>
<nom>COMMUNICATION</nom>
<nom>XML</nom>
<nom>Algorithmique et recherche opérationnelle</nom>
<nom>Intelligence artificielle</nom>
<nom>Programmation parallèle</nom>
<nom>Projet</nom>
<nom>Stage de deux mois</nom>
<nom>Sémantique</nom>
<nom>Intégration des systèmes d'information</nom>
<nom>Initiation à la fouille de données et à l'optimisation des SGBD</nom>
<nom>Algorithme à performance garantie</nom>
<nom>Introduction à l'apprentissage automatique</nom>
<nom>Génie Logiciel</nom>
<nom>Complexité</nom>
<nom>Réseaux</nom>
<nom>Programmation fonctionnelle</nom>
<nom>Programmation logique</nom>
<nom>Outils de l'internet</nom>
<nom>Système embarqué</nom>
<nom>Fondamentaux pour l'ingénierie des langues</nom>
<nom>Modèles à évènements discrets</nom>
<nom>BDR : approfondissement</nom>
<nom>SPORT</nom>
<nom>Qualité logicielle : outils et méthodes</nom>
<nom>Spécification logicielle</nom>
<nom>Conception logicielle</nom>
<nom>Architecture logicielle JEE</nom>
<nom>Technologies du Web et Web 2.0 </nom>
<nom>XML avancé</nom>
<nom>Anglais 2</nom>
<nom>Gestion de projet</nom>
<nom>Communication 2 </nom>
</enseignements>
